nostr_relay/__init__.py
nostr_relay/alembic.ini
nostr_relay/asgi.py
nostr_relay/auth.py
nostr_relay/cli.py
nostr_relay/config.py
nostr_relay/config.yaml
nostr_relay/dynamic_lists.py
nostr_relay/errors.py
nostr_relay/foaf.py
nostr_relay/monkeypatch.py
nostr_relay/notifier.py
nostr_relay/purple.py
nostr_relay/rate_limiter.py
nostr_relay/util.py
nostr_relay/validators.py
nostr_relay/verification.py
nostr_relay/web.py
nostr_relay/alembic/README
nostr_relay/alembic/env.py
nostr_relay/alembic/script.py.mako
nostr_relay/alembic/versions/63a13fc870a3_add_indexes.py
nostr_relay/alembic/versions/e748549d8d91_initial_tables.py
nostr_relay/alembic/versions/fb1b3b1247a1_migrate_old_data.py
nostr_relay/recipe/__init__.py
nostr_relay/recipe/homeserver.py
nostr_relay/storage/__init__.py
nostr_relay/storage/base.py
nostr_relay/storage/db.py
nostr_relay/storage/kv.py
nostr_relay-1.14.dist-info/LICENSE.txt
nostr_relay-1.14.dist-info/METADATA
nostr_relay-1.14.dist-info/WHEEL
nostr_relay-1.14.dist-info/entry_points.txt
nostr_relay-1.14.dist-info/top_level.txt
nostr_relay-1.14.dist-info/zip-safe
nostr_relay-1.14.dist-info/RECORD
