Metadata-Version: 2.1
Name: nostr_relay
Version: 1.14
Summary: nostr relay
Home-page: https://code.pobblelabs.org/nostr_relay
Author: Dave St.Germain
Author-email: dave@st.germa.in
License: BSD 3-Clause License
Keywords: protocol
Classifier: License :: OSI Approved :: BSD License
Classifier: Programming Language :: Python :: 3
Classifier: Programming Language :: Python :: 3.9
Classifier: Programming Language :: Python :: 3.10
Classifier: Programming Language :: Python :: 3.11
Classifier: Programming Language :: Python :: 3.12
Classifier: Development Status :: 5 - Production/Stable
Classifier: Environment :: Web Environment
Classifier: Intended Audience :: System Administrators
Classifier: Operating System :: OS Independent
Classifier: Topic :: Internet :: WWW/HTTP
Requires-Python: >=3.9
License-File: LICENSE.txt
Requires-Dist: falcon
Requires-Dist: aionostr >=0.20.0
Requires-Dist: sqlalchemy[asyncio] >=2.0
Requires-Dist: aiosqlite >=0.20.0
Requires-Dist: aiohttp[speedups]
Requires-Dist: uvicorn[standard]
Requires-Dist: gunicorn
Requires-Dist: setproctitle
Requires-Dist: alembic
Requires-Dist: pydantic >2.0
Requires-Dist: wsproto ; platform_python_implementation != "CPython"
Requires-Dist: python-rapidjson ; platform_python_implementation == "CPython"
Requires-Dist: async-timeout ; python_version < "3.11.0"
Provides-Extra: lmdb
Requires-Dist: lmdb ; extra == 'lmdb'
Requires-Dist: msgpack ; extra == 'lmdb'
Requires-Dist: whoosh ; extra == 'lmdb'
Provides-Extra: postgres
Requires-Dist: asyncpg ; extra == 'postgres'
Provides-Extra: test
Requires-Dist: pytest ; extra == 'test'
Requires-Dist: pytest-cov ; extra == 'test'
Requires-Dist: pytest-asyncio ; extra == 'test'
Requires-Dist: pytest-xdist ; extra == 'test'
